nebulib/__init__.py
nebulib/monitor.py
nebulib-0.3.dist-info/METADATA
nebulib-0.3.dist-info/WHEEL
nebulib-0.3.dist-info/top_level.txt
nebulib-0.3.dist-info/RECORD
