Metadata-Version: 2.4
Name: nebulib
Version: 0.3
Summary: A performance-focused system monitor library.
Author: XZRDev
License: MIT
Requires-Dist: psutil
Dynamic: author
Dynamic: description
Dynamic: description-content-type
Dynamic: license
Dynamic: requires-dist
Dynamic: summary
